eufylife_ble/__init__.py
eufylife_ble/auth_handler.py
eufylife_ble/client.py
eufylife_ble/exceptions.py
eufylife_ble/models.py
eufylife_ble/util.py
eufylife_ble-0.2.1.dist-info/METADATA
eufylife_ble-0.2.1.dist-info/WHEEL
eufylife_ble-0.2.1.dist-info/RECORD
