Metadata-Version: 2.1
Name: eufylife_ble
Version: 0.2.1
Summary: A library to communicate with EufyLife Bluetooth devices.
Home-page: https://github.com/MatthewBCooke/eufylife_ble
License: MIT
Author: Matthew Cooke
Author-email: matthew.cooke14@gmail.com
Requires-Python: >=3.9,<4.0
Classifier: License :: OSI Approved :: MIT License
Classifier: Programming Language :: Python :: 3
Classifier: Programming Language :: Python :: 3.9
Classifier: Programming Language :: Python :: 3.10
Classifier: Programming Language :: Python :: 3.11
Classifier: Programming Language :: Python :: 3.12
Classifier: Programming Language :: Python :: 3.13
Requires-Dist: bleak (>=0.19.0)
Requires-Dist: bleak-retry-connector (>=2.3.0)
Requires-Dist: cryptography (>=39.0)
